Metadata-Version: 2.1
Name: phoning-home
Version: 0.1.0
Summary: Phoning home, analytics and storage with 0 setup.
Home-page: https://github.com/Abdur-RahmaanJ/phoning-home
Author: Abdur-Rahmaan Janhangeer
Author-email: arj.python@gmail.com
Project-URL: Bug Reports, https://github.com/Abdur-RahmaanJ/phoning-home/issues
Project-URL: Source, https://github.com/Abdur-RahmaanJ/phoning-home/
Keywords: phoning-home analytics cloud storage
Classifier: Development Status :: 3 - Alpha
Classifier: Intended Audience :: Developers
Classifier: License :: OSI Approved :: MIT License
Classifier: Programming Language :: Python :: 3.4
Classifier: Programming Language :: Python :: 3.5
Classifier: Programming Language :: Python :: 3.6
Classifier: Programming Language :: Python :: 3.7
Classifier: Programming Language :: Python :: 3.8
Classifier: Programming Language :: Python :: 3.9
Classifier: Programming Language :: Python :: 3.10
Classifier: Programming Language :: Python :: 3.11
Requires-Python: >=3.4
License-File: LICENSE
